Workbook

Sheet Bank Statement
A1: Date | B1: Amount (INR) | C1: Reference | D1: Description
A2: 45778 | B2: 50000 | C2: REF123456 | D2: Salary Credit
A3: 45780 | B3: -5000 | C3: REF345678 | D3: Electricity Bill - Tata
A4: 45782 | B4: -1200 | C4: REF120045 | D4: Phone Bill - Airtel
A5: 45785 | B5: -10000 | C5: REF784512 | D5: Rent Payment - May
A6: 45792 | B6: 75000 | C6: REF741258 | D6: Client Payment Inv#205
A7: 45798 | B7: -1500 | C7: REF698745 | D7: Internet Charges - ACT
A8: 45802 | B8: -8000 | C8: REF963258 | D8: Office Supplies - Staples
A9: 45807 | B9: -2500 | C9: REF487512 | D9: Zomato Food Reimbursement

Sheet GL
A1: Date | B1: Amount (INR) | C1: Reference | D1: Description
A2: 45778 | B2: 50000 | C2: REF123456 | D2: Salary A/c – April
A3: 45780 | B3: -5000 | C3: REF345678 | D3: Power Utility - Tata
A4: 45782 | B4: -1250 | C4: REF120045 | D4: Airtel Recharge
A5: 45785 | B5: -10000 | C5: REF784512 | D5: Rent Transfer for May
A6: 45792 | B6: 75000 | C6: REF741258 | D6: Client Receipt – Invoice 205
A7: 45798 | B7: -1500 | C7: REF698745 | D7: Broadband – ACT Fibernet
A8: 45802 | B8: -7800 | C8: REF963258 | D8: Supplies – Stationery
A9: 45807 | B9: -2500 | C9: REF487512 | D9: Zomato – Team Lunch
A10: 45808 | B10: -3000 | C10: REF159357 | D10: Miscellaneous Expense

Sheet Reconciliation
A1: Date | B1: Amount (INR) | C1: Reference | D1: Description | E1: matched reference | F1: Exact Match | G1: Fuzzymatch | H1: Bank description | I1: recurring pattern
A2: 45778 | B2: 50000 | C2: REF123456 | D2: Salary A/c – April | E2: =VLOOKUP(C2,'Bank Statement'!$C$1:$C$9,1,0) -> REF123456 | F2: =_xlfn.XLOOKUP(E2,'Bank Statement'!$C$1:$C$9,'Bank Statement'!$B$1:$B$9,1,0) -> 50000 | G2: =F2-B2 -> 0 | H2: =_xlfn.XLOOKUP(E2,'Bank Statement'!$C$1:$C$9,'Bank Statement'!$D$1:$D$9,1,0) -> Salary Credit
A3: 45780 | B3: -5000 | C3: REF345678 | D3: Power Utility - Tata | E3: =VLOOKUP(C3,'Bank Statement'!$C$1:$C$9,1,0) -> REF345678 | F3: =_xlfn.XLOOKUP(E3,'Bank Statement'!$C$1:$C$9,'Bank Statement'!$B$1:$B$9,1,0) -> -5000 | G3: =F3-B3 -> 0 | H3: =_xlfn.XLOOKUP(E3,'Bank Statement'!$C$1:$C$9,'Bank Statement'!$D$1:$D$9,1,0) -> Electricity Bill - Tata
A4: 45782 | B4: -1250 | C4: REF120045 | D4: Airtel Recharge | E4: =VLOOKUP(C4,'Bank Statement'!$C$1:$C$9,1,0) -> REF120045 | F4: =_xlfn.XLOOKUP(E4,'Bank Statement'!$C$1:$C$9,'Bank Statement'!$B$1:$B$9,1,0) -> -1200 | G4: =F4-B4 -> 50 | H4: =_xlfn.XLOOKUP(E4,'Bank Statement'!$C$1:$C$9,'Bank Statement'!$D$1:$D$9,1,0) -> Phone Bill - Airtel
A5: 45785 | B5: -10000 | C5: REF784512 | D5: Rent Transfer for May | E5: =VLOOKUP(C5,'Bank Statement'!$C$1:$C$9,1,0) -> REF784512 | F5: =_xlfn.XLOOKUP(E5,'Bank Statement'!$C$1:$C$9,'Bank Statement'!$B$1:$B$9,1,0) -> -10000 | G5: =F5-B5 -> 0 | H5: =_xlfn.XLOOKUP(E5,'Bank Statement'!$C$1:$C$9,'Bank Statement'!$D$1:$D$9,1,0) -> Rent Payment - May
A6: 45792 | B6: 75000 | C6: REF741258 | D6: Client Receipt – Invoice 205 | E6: =VLOOKUP(C6,'Bank Statement'!$C$1:$C$9,1,0) -> REF741258 | F6: =_xlfn.XLOOKUP(E6,'Bank Statement'!$C$1:$C$9,'Bank Statement'!$B$1:$B$9,1,0) -> 75000 | G6: =F6-B6 -> 0 | H6: =_xlfn.XLOOKUP(E6,'Bank Statement'!$C$1:$C$9,'Bank Statement'!$D$1:$D$9,1,0) -> Client Payment Inv#205
A7: 45798 | B7: -1500 | C7: REF698745 | D7: Broadband – ACT Fibernet | E7: =VLOOKUP(C7,'Bank Statement'!$C$1:$C$9,1,0) -> REF698745 | F7: =_xlfn.XLOOKUP(E7,'Bank Statement'!$C$1:$C$9,'Bank Statement'!$B$1:$B$9,1,0) -> -1500 | G7: =F7-B7 -> 0 | H7: =_xlfn.XLOOKUP(E7,'Bank Statement'!$C$1:$C$9,'Bank Statement'!$D$1:$D$9,1,0) -> Internet Charges - ACT
A8: 45802 | B8: -7800 | C8: REF963258 | D8: Supplies – Stationery | E8: =VLOOKUP(C8,'Bank Statement'!$C$1:$C$9,1,0) -> REF963258 | F8: =_xlfn.XLOOKUP(E8,'Bank Statement'!$C$1:$C$9,'Bank Statement'!$B$1:$B$9,1,0) -> -8000 | G8: =F8-B8 -> -200 | H8: =_xlfn.XLOOKUP(E8,'Bank Statement'!$C$1:$C$9,'Bank Statement'!$D$1:$D$9,1,0) -> Office Supplies - Staples
A9: 45807 | B9: -2500 | C9: REF487512 | D9: Zomato – Team Lunch | E9: =VLOOKUP(C9,'Bank Statement'!$C$1:$C$9,1,0) -> REF487512 | F9: =_xlfn.XLOOKUP(E9,'Bank Statement'!$C$1:$C$9,'Bank Statement'!$B$1:$B$9,1,0) -> -2500 | G9: =F9-B9 -> 0 | H9: =_xlfn.XLOOKUP(E9,'Bank Statement'!$C$1:$C$9,'Bank Statement'!$D$1:$D$9,1,0) -> Zomato Food Reimbursement
A10: 45808 | B10: -3000 | C10: REF159357 | D10: Miscellaneous Expense | E10: =VLOOKUP(C10,'Bank Statement'!$C$1:$C$9,1,0) -> #N/A | F10: =_xlfn.XLOOKUP(E10,'Bank Statement'!$C$1:$C$9,'Bank Statement'!$B$1:$B$9,1,0) -> #N/A | G10: =F10-B10 -> #N/A | H10: =_xlfn.XLOOKUP(E10,'Bank Statement'!$C$1:$C$9,'Bank Statement'!$D$1:$D$9,1,0) -> #N/A
